compressor_postcss/__init__.py
django_compressor_postcss-0.8.2.data/data/LICENSE
django_compressor_postcss-0.8.2.data/data/README.md
django_compressor_postcss-0.8.2.dist-info/DESCRIPTION.rst
django_compressor_postcss-0.8.2.dist-info/METADATA
django_compressor_postcss-0.8.2.dist-info/RECORD
django_compressor_postcss-0.8.2.dist-info/WHEEL
django_compressor_postcss-0.8.2.dist-info/metadata.json
django_compressor_postcss-0.8.2.dist-info/top_level.txt
