Metadata-Version: 2.0
Name: django-compressor-postcss
Version: 0.8.2
Summary: PostCSS support for django-compressor
Home-page: https://github.com/pithikos/django-compressor-postcss
Author: Johan Hanssen Seferidis
Author-email: manossef@gmail.com
License: MIT
Keywords: django-compressor django postcss post-processing css web-development autoprefixer
Platform: UNKNOWN
Classifier: Intended Audience :: Developers
Classifier: License :: OSI Approved :: MIT License
Classifier: Framework :: Django
Classifier: Topic :: Software Development :: Libraries
Classifier: Environment :: Web Environment
Classifier: Environment :: Plugins
Requires-Dist: django
Requires-Dist: django-compressor
